tally/__init__.py
tally/client.py
tally/exceptions.py
tally/models/__init__.py
tally/models/block_payloads.py
tally/models/form.py
tally/models/invite.py
tally/models/user.py
tally/models/webhook.py
tally/models/workspace.py
tally/py.typed
tally/resources/__init__.py
tally/resources/forms.py
tally/resources/organizations.py
tally/resources/users.py
tally/resources/webhooks.py
tally/resources/workspaces.py
pytally_sdk-0.1.9.dist-info/WHEEL
pytally_sdk-0.1.9.dist-info/METADATA
pytally_sdk-0.1.9.dist-info/RECORD
