Metadata-Version: 2.4
Name: pytally-sdk
Version: 0.1.9
Summary: Unofficial Python SDK for the Tally.so API
Keywords: tally,forms,api,sdk,tally.so,form-builder
Author: Felipe Adeildo
Author-email: Felipe Adeildo <contato@felipeadeildo.com>
License-Expression: Apache-2.0
Classifier: Development Status :: 3 - Alpha
Classifier: Intended Audience :: Developers
Classifier: License :: OSI Approved :: Apache Software License
Classifier: Programming Language :: Python :: 3
Classifier: Programming Language :: Python :: 3.11
Classifier: Programming Language :: Python :: 3.12
Classifier: Programming Language :: Python :: 3.13
Classifier: Topic :: Software Development :: Libraries :: Python Modules
Requires-Dist: httpx>=0.28.1
Requires-Python: >=3.11
Project-URL: Documentation, https://pytally-sdk.fa.dev.br/
Project-URL: Homepage, https://github.com/felipeadeildo/pytally-sdk
Project-URL: Issues, https://github.com/felipeadeildo/pytally-sdk/issues
Project-URL: Repository, https://github.com/felipeadeildo/pytally-sdk
